MANIFEST.in
README.md
setup.py
AuthZ_Group.egg-info/PKG-INFO
AuthZ_Group.egg-info/SOURCES.txt
AuthZ_Group.egg-info/dependency_links.txt
AuthZ_Group.egg-info/requires.txt
AuthZ_Group.egg-info/top_level.txt
authz_group/VERSION
authz_group/__init__.py
authz_group/models.py
authz_group/tests.py
authz_group/urls.py
authz_group/views.py
authz_group/authz_implementation/__init__.py
authz_group/authz_implementation/all_fail.py
authz_group/authz_implementation/all_ok.py
authz_group/authz_implementation/settings.py
authz_group/authz_implementation/solstice.py
authz_group/authz_implementation/uw_group_service.py
authz_group/migrations/0001_initial.py
authz_group/migrations/__init__.py
authz_group/static/css/crowds.css
authz_group/static/js/crowd_demo.js
authz_group/static/js/crowds.js
authz_group/templates/crowds_demo.html
authz_group/templates/crowd_control/js.html
authz_group/templates/crowd_control/styles.html
authz_group/templates/crowd_control/templates.html
authz_group/templates/crowd_control/handlebars/group_list.html
authz_group/templatetags/__init__.py
authz_group/templatetags/templatetag_crowd_control.py