Metadata-Version: 1.1
Name: AuthZ-Group
Version: 1.6
Summary: A library for managing access with groups
Home-page: https://github.com/uw-it-aca/authz_group
Author: UW-IT AXDD
Author-email: aca-it@uw.edu
License: Apache License, Version 2.0
Platform: UNKNOWN
Classifier: Intended Audience :: Developers
Classifier: License :: OSI Approved :: Apache Software License
Classifier: Operating System :: OS Independent
Classifier: Programming Language :: Python
Classifier: Programming Language :: Python :: 2.7
Classifier: Programming Language :: Python :: 3.4
